dirconfig/__init__.py
tests/__init__.py
tests/test_add_to_path.py
tests/test_organize_files.py
dirconfig-0.2.6.dist-info/LICENSE
dirconfig-0.2.6.dist-info/METADATA
dirconfig-0.2.6.dist-info/WHEEL
dirconfig-0.2.6.dist-info/entry_points.txt
dirconfig-0.2.6.dist-info/top_level.txt
dirconfig-0.2.6.dist-info/RECORD
