Metadata-Version: 2.1
Name: dirconfig
Version: 0.2.6
Summary: A simple directory configuration tool
Home-page: https://github.com/judahpaul16/dirconfig
Author: Judah Paul
Author-email: me@judahpaul.com
License: UNKNOWN
Platform: UNKNOWN
Classifier: Programming Language :: Python :: 3
Classifier: License :: OSI Approved :: MIT License
Classifier: Operating System :: OS Independent
Requires-Python: >=3.6
Requires-Dist: PyYAML ==6.0.1
Requires-Dist: watchdog ==4.0.0
Requires-Dist: urbackup-server-web-api-wrapper ==0.11
